LICENSE
MANIFEST.in
setup.py
django_redis_sentinel/__init__.py
django_redis_sentinel/cache.py
django_redis_sentinel/pool.py
django_redis_sentinel/client/__init__.py
django_redis_sentinel/client/sentinel.py
django_redis_sentinel_redux.egg-info/PKG-INFO
django_redis_sentinel_redux.egg-info/SOURCES.txt
django_redis_sentinel_redux.egg-info/dependency_links.txt
django_redis_sentinel_redux.egg-info/not-zip-safe
django_redis_sentinel_redux.egg-info/requires.txt
django_redis_sentinel_redux.egg-info/top_level.txt
tests/README.txt
tests/runtests-sentinel.py
tests/test_sqlite_sentinel.py
tests/urls.py
tests/hashring_test/__init__.py
tests/hashring_test/models.py
tests/hashring_test/tests.py
tests/redis_backend_testapp/__init__.py
tests/redis_backend_testapp/models.py
tests/redis_backend_testapp/tests.py